weather4bar/__init__.py
weather4bar/weather4bar.py
weather4bar-1.0.2.dist-info/METADATA
weather4bar-1.0.2.dist-info/WHEEL
weather4bar-1.0.2.dist-info/licenses/LICENSE
weather4bar-1.0.2.dist-info/RECORD
