Metadata-Version: 2.3
Name: weather4bar
Version: 1.0.2
Summary: A Python script that shows weather info for the current location.
Project-URL: Homepage, https://github.com/Andy3153/weather4bar
Project-URL: Issues, https://github.com/Andy3153/weather4bar/issues
Author-email: Andrei Dobrete <andy3153@protonmail.com>
License-File: LICENSE
Classifier: Development Status :: 5 - Production/Stable
Classifier: Environment :: X11 Applications
Classifier: Intended Audience :: End Users/Desktop
Classifier: License :: OSI Approved :: GNU General Public License v2 (GPLv2)
Classifier: Natural Language :: English
Classifier: Operating System :: POSIX :: Linux
Classifier: Programming Language :: Python :: 3.12
Classifier: Topic :: Desktop Environment :: Window Managers
Classifier: Topic :: System :: Monitoring
Classifier: Topic :: Utilities
Requires-Python: >=3.12
Requires-Dist: requests>=2.32.3
